{"Universidad Tecnol\u00f3gica de Chihuahua": {"Country": "Mexico", "Works": {"2025": 0, "2024": 15, "2023": 16, "2022": 13, "2021": 11, "2020": 7, "2019": 15, "2018": 5, "2017": 8, "2016": 9, "2015": 6, "2014": 1, "2013": 1, "2012": 0}}, "Howard Community College": {"Country": "United States", "Works": {"2025": 0, "2024": 7, "2023": 5, "2022": 6, "2021": 4, "2020": 7, "2019": 4, "2018": 8, "2017": 4, "2016": 9, "2015": 5, "2014": 5, "2013": 4, "2012": 3}}, "Delgado Community College": {"Country": "United States", "Works": {"2025": 2, "2024": 10, "2023": 3, "2022": 8, "2021": 4, "2020": 5, "2019": 1, "2018": 1, "2017": 1, "2016": 6, "2015": 1, "2014": 4, "2013": 5, "2012": 4}}, "Northeastern Oklahoma A&M College": {"Country": "United States", "Works": {"2025": 0, "2024": 0, "2023": 0, "2022": 0, "2021": 0, "2020": 0, "2019": 0, "2018": 3, "2017": 0, "2016": 0, "2015": 1, "2014": 0, "2013": 2, "2012": 2}}, "Northern Essex Community College": {"Country": "United States", "Works": {"2025": 1, "2024": 0, "2023": 0, "2022": 0, "2021": 2, "2020": 15, "2019": 3, "2018": 1, "2017": 5, "2016": 4, "2015": 4, "2014": 2, "2013": 1, "2012": 7}}, "Center for Art and Media Karlsruhe": {"Country": "Germany", "Works": {"2025": 0, "2024": 1, "2023": 5, "2022": 6, "2021": 11, "2020": 8, "2019": 4, "2018": 8, "2017": 7, "2016": 1, "2015": 1, "2014": 1, "2013": 3, "2012": 3}}, "Hong Kong Academy for Performing Arts": {"Country": "Hong Kong", "Works": {"2025": 4, "2024": 7, "2023": 16, "2022": 22, "2021": 17, "2020": 11, "2019": 6, "2018": 2, "2017": 6, "2016": 0, "2015": 1, "2014": 1, "2013": 3, "2012": 0}}, "Universidad Hebraica": {"Country": "Mexico", "Works": {"2025": 0, "2024": 0, "2023": 5, "2022": 4, "2021": 3, "2020": 5, "2019": 3, "2018": 5, "2017": 1, "2016": 2, "2015": 4, "2014": 2, "2013": 11, "2012": 1}}, "\u00c9cole Sup\u00e9rieure Multinationale des T\u00e9l\u00e9communications": {"Country": "Senegal", "Works": {"2025": 3, "2024": 3, "2023": 4, "2022": 11, "2021": 7, "2020": 15, "2019": 6, "2018": 21, "2017": 4, "2016": 14, "2015": 8, "2014": 5, "2013": 2, "2012": 2}}, "Christian Family Service Centre": {"Country": "Hong Kong", "Works": {"2025": 4, "2024": 9, "2023": 11, "2022": 10, "2021": 11, "2020": 7, "2019": 11, "2018": 5, "2017": 7, "2016": 8, "2015": 2, "2014": 2, "2013": 3, "2012": 2}}, "Institut Catholique d'Arts et M\u00e9tiers": {"Country": "France", "Works": {"2025": 2, "2024": 10, "2023": 15, "2022": 9, "2021": 10, "2020": 3, "2019": 5, "2018": 2, "2017": 12, "2016": 7, "2015": 3, "2014": 8, "2013": 2, "2012": 2}}, "Lamar State College\u2013Port Arthur": {"Country": "United States", "Works": {"2025": 0, "2024": 0, "2023": 0, "2022": 2, "2021": 12, "2020": 1, "2019": 2, "2018": 1, "2017": 1, "2016": 4, "2015": 2, "2014": 0, "2013": 1, "2012": 0}}, "Al-Khair University": {"Country": "Pakistan", "Works": {"2025": 1, "2024": 10, "2023": 20, "2022": 11, "2021": 14, "2020": 9, "2019": 7, "2018": 1, "2017": 6, "2016": 5, "2015": 4, "2014": 2, "2013": 9, "2012": 4}}, "Reial Acad\u00e8mia de Ci\u00e8ncies i Arts de Barcelona": {"Country": "Spain", "Works": {"2025": 12, "2024": 17, "2023": 12, "2022": 9, "2021": 2, "2020": 2, "2019": 3, "2018": 1, "2017": 6, "2016": 6, "2015": 18, "2014": 2, "2013": 4, "2012": 2}}, "LUdeS University": {"Country": "Switzerland", "Works": {"2025": 3, "2024": 8, "2023": 16, "2022": 12, "2021": 3, "2020": 6, "2019": 4, "2018": 2, "2017": 11, "2016": 5, "2015": 4, "2014": 10, "2013": 7, "2012": 5}}, "Episcopal High School": {"Country": "United States", "Works": {"2025": 3, "2024": 7, "2023": 13, "2022": 7, "2021": 6, "2020": 1, "2019": 3, "2018": 3, "2017": 6, "2016": 7, "2015": 11, "2014": 9, "2013": 6, "2012": 1}}, "Weldon City Schools": {"Country": "United States", "Works": {"2025": 3, "2024": 2, "2023": 4, "2022": 3, "2021": 4, "2020": 5, "2019": 7, "2018": 3, "2017": 9, "2016": 7, "2015": 2, "2014": 4, "2013": 4, "2012": 1}}, "Center for Business Studies": {"Country": "Switzerland", "Works": {"2025": 0, "2024": 5, "2023": 16, "2022": 3, "2021": 8, "2020": 5, "2019": 11, "2018": 4, "2017": 5, "2016": 3, "2015": 1, "2014": 0, "2013": 1, "2012": 2}}, "Apex School of Theology": {"Country": "United States", "Works": {"2025": 2, "2024": 10, "2023": 9, "2022": 4, "2021": 4, "2020": 12, "2019": 4, "2018": 3, "2017": 0, "2016": 17, "2015": 2, "2014": 5, "2013": 2, "2012": 0}}, "Saturday Academy": {"Country": "United States", "Works": {"2025": 0, "2024": 3, "2023": 5, "2022": 1, "2021": 2, "2020": 4, "2019": 2, "2018": 1, "2017": 5, "2016": 2, "2015": 4, "2014": 3, "2013": 0, "2012": 0}}, "Sabzevar University of New Technology": {"Country": "Iran", "Works": {"2025": 0, "2024": 0, "2023": 0, "2022": 1, "2021": 6, "2020": 33, "2019": 21, "2018": 19, "2017": 10, "2016": 3, "2015": 1, "2014": 0, "2013": 0, "2012": 1}}, "Hara University": {"Country": "Afghanistan", "Works": {"2025": 3, "2024": 4, "2023": 30, "2022": 17, "2021": 9, "2020": 5, "2019": 6, "2018": 7, "2017": 6, "2016": 4, "2015": 1, "2014": 2, "2013": 2, "2012": 4}}, "Jizzakh branch of the National University of Uzbekistan named after Mirzo Ulugbek": {"Country": "Uzbekistan", "Works": {"2025": 1, "2024": 11, "2023": 53, "2022": 31, "2021": 14}}, "William Woods University": {"Country": "United States", "Works": {"2025": 2, "2024": 6, "2023": 5, "2022": 3, "2021": 10, "2020": 5, "2019": 2, "2018": 4, "2017": 2, "2016": 3, "2015": 3, "2014": 4, "2013": 3, "2012": 2}}, "American Association of Community Colleges": {"Country": "United States", "Works": {"2025": 0, "2024": 0, "2023": 0, "2022": 1, "2021": 2, "2020": 2, "2019": 2, "2018": 0, "2017": 3, "2016": 2, "2015": 0, "2014": 0, "2013": 1, "2012": 4}}, "Coastline Community College": {"Country": "United States", "Works": {"2025": 0, "2024": 0, "2023": 1, "2022": 4, "2021": 0, "2020": 2, "2019": 5, "2018": 8, "2017": 7, "2016": 11, "2015": 14, "2014": 2, "2013": 11, "2012": 10}}, "City of Bristol College": {"Country": "United Kingdom", "Works": {"2025": 0, "2024": 0, "2023": 1, "2022": 1, "2021": 3, "2020": 3, "2019": 5, "2018": 3, "2017": 5, "2016": 3, "2015": 4, "2014": 5, "2013": 0, "2012": 4}}, "Minobusan University": {"Country": "Japan", "Works": {"2025": 0, "2024": 2, "2023": 1, "2022": 1, "2021": 2, "2020": 2, "2019": 1, "2018": 1, "2017": 1, "2016": 0, "2015": 2, "2014": 0, "2013": 1, "2012": 1}}, "Keisen University": {"Country": "Japan", "Works": {"2025": 0, "2024": 1, "2023": 3, "2022": 6, "2021": 6, "2020": 7, "2019": 5, "2018": 4, "2017": 5, "2016": 0, "2015": 5, "2014": 5, "2013": 5, "2012": 2}}, "Daekyeung University": {"Country": "South Korea", "Works": {"2025": 1, "2024": 4, "2023": 3, "2022": 4, "2021": 8, "2020": 10, "2019": 15, "2018": 6, "2017": 12, "2016": 11, "2015": 7, "2014": 6, "2013": 4, "2012": 6}}, "Universidad Cat\u00f3lica de Costa Rica": {"Country": "Costa Rica", "Works": {"2025": 1, "2024": 3, "2023": 9, "2022": 7, "2021": 4, "2020": 5, "2019": 4, "2018": 8, "2017": 6, "2016": 4, "2015": 5, "2014": 3, "2013": 6, "2012": 3}}, "Westfalen-Kolleg": {"Country": "Germany", "Works": {"2025": 0, "2024": 1, "2023": 3, "2022": 1, "2021": 1, "2020": 4, "2019": 0, "2018": 3, "2017": 1, "2016": 1, "2015": 2, "2014": 1, "2013": 2, "2012": 2}}, "Resource Conservation District of Santa Cruz County": {"Country": "United States", "Works": {"2025": 1, "2024": 0, "2023": 0, "2022": 1, "2021": 1, "2020": 3, "2019": 4, "2018": 7, "2017": 3, "2016": 5, "2015": 4, "2014": 4, "2013": 4, "2012": 4}}, "Siberian State Order of the Red Banner of Labor Research Institute of Metrology": {"Country": "Russia", "Works": {"2025": 0, "2024": 1, "2023": 0, "2022": 3, "2021": 1, "2020": 1, "2019": 6, "2018": 6, "2017": 0, "2016": 9, "2015": 0, "2014": 12, "2013": 2, "2012": 14}}, "Staropolska Szko\u0142a Wy\u017csza w Kielcach": {"Country": "Poland", "Works": {"2025": 0, "2024": 2, "2023": 8, "2022": 4, "2021": 0, "2020": 4, "2019": 3, "2018": 2, "2017": 4, "2016": 0, "2015": 5, "2014": 4, "2013": 2, "2012": 1}}, "Samtskhe-Javakheti State University": {"Country": "Georgia", "Works": {"2025": 1, "2024": 11, "2023": 11, "2022": 12, "2021": 22, "2020": 21, "2019": 15, "2018": 7, "2017": 2, "2015": 1, "2014": 1, "2013": 1}}, "Paraguayan Center for Population Studies": {"Country": "Paraguay", "Works": {"2025": 2, "2024": 12, "2023": 10, "2022": 4, "2021": 13, "2020": 8, "2019": 8, "2018": 7, "2017": 6, "2016": 2, "2015": 3, "2014": 3, "2013": 2, "2012": 4}}, "Universidad para el Desarrollo Andino": {"Country": "Peru", "Works": {"2025": 1, "2024": 5, "2023": 7, "2022": 10, "2021": 15, "2020": 6, "2019": 5, "2018": 12, "2017": 6, "2016": 7, "2015": 8, "2014": 9, "2013": 1, "2012": 4}}, "Universidad Escuela Libre de Derecho": {"Country": "Costa Rica", "Works": {"2024": 6, "2023": 4, "2022": 4, "2021": 5, "2020": 1, "2019": 4, "2018": 2, "2017": 6, "2016": 10, "2015": 8, "2014": 4, "2013": 6, "2012": 10}}, "C\u00e9gep Limoilou": {"Country": "Canada", "Works": {"2025": 1, "2024": 2, "2023": 0, "2022": 1, "2021": 1, "2020": 3, "2019": 1, "2018": 0, "2017": 1, "2016": 2, "2015": 6, "2014": 2, "2013": 8, "2012": 9}}, "Borno State University": {"Country": "Nigeria", "Works": {"2025": 1, "2024": 13, "2023": 42, "2022": 51, "2021": 2}}, "Mount Kigali University": {"Country": "Rwanda", "Works": {"2025": 2, "2024": 32, "2023": 20, "2022": 11, "2021": 19, "2020": 14, "2019": 5, "2018": 2, "2017": 4}}, "Haute \u00e9cole de travail social et de la sant\u00e9 Lausanne - HETSL, HES-SO": {"Country": "Switzerland", "Works": {"2025": 1, "2024": 10, "2023": 8, "2022": 20, "2021": 28, "2020": 9, "2019": 4, "2018": 1, "2017": 1, "2016": 1, "2015": 1, "2014": 0, "2013": 0, "2012": 8}}, "Instituto Tecnol\u00f3gico de Ciudad Guzm\u00e1n": {"Country": "Mexico", "Works": {"2025": 4, "2024": 10, "2023": 14, "2022": 7, "2021": 5, "2020": 7, "2019": 9, "2018": 12, "2017": 6, "2016": 2, "2015": 1, "2014": 3, "2013": 1, "2012": 0}}, "Memphis Theological Seminary": {"Country": "United States", "Works": {"2025": 0, "2024": 2, "2023": 5, "2022": 2, "2021": 1, "2020": 3, "2019": 5, "2018": 3, "2017": 7, "2016": 1, "2015": 2, "2014": 1, "2013": 0, "2012": 1}}, "Des Moines Area Community College": {"Country": "United States", "Works": {"2025": 1, "2024": 2, "2023": 1, "2022": 3, "2021": 3, "2020": 5, "2019": 1, "2018": 6, "2017": 4, "2016": 4, "2015": 5, "2014": 6, "2013": 5, "2012": 1}}, "Yamaguchi Junior College": {"Country": "Japan", "Works": {"2025": 0, "2024": 2, "2023": 3, "2022": 2, "2021": 3, "2020": 4, "2019": 1, "2018": 1, "2017": 1, "2016": 2, "2015": 0, "2014": 1, "2013": 4, "2012": 6}}, "Olympic College": {"Country": "United States", "Works": {"2025": 0, "2024": 7, "2023": 5, "2022": 9, "2021": 6, "2020": 3, "2019": 4, "2018": 1, "2017": 2, "2016": 2, "2015": 4, "2014": 4, "2013": 3, "2012": 4}}, "Becker College": {"Country": "United States", "Works": {"2025": 0, "2024": 2, "2023": 1, "2022": 6, "2021": 2, "2020": 10, "2019": 3, "2018": 9, "2017": 10, "2016": 5, "2015": 5, "2014": 4, "2013": 10, "2012": 7}}, "Regenesys Business School": {"Country": "South Africa", "Works": {"2025": 3, "2024": 10, "2023": 19, "2022": 8, "2021": 3, "2020": 4, "2019": 6, "2018": 1, "2017": 7, "2016": 8, "2015": 9, "2014": 18, "2013": 6, "2012": 0}}, "Shanti Business School": {"Country": "India", "Works": {"2025": 4, "2024": 5, "2023": 3, "2022": 4, "2021": 5, "2020": 1, "2019": 6, "2018": 4, "2017": 4, "2016": 11, "2015": 3, "2014": 3, "2013": 5, "2012": 10}}, "Sheridan College": {"Country": "United States", "Works": {"2025": 3, "2024": 5, "2023": 2, "2022": 6, "2021": 8, "2020": 2, "2019": 1, "2018": 3, "2017": 10, "2016": 3, "2015": 3, "2014": 2, "2013": 8, "2012": 5}}, "Universidad de Concepci\u00f3n del Uruguay": {"Country": "Argentina", "Works": {"2025": 2, "2024": 12, "2023": 8, "2022": 6, "2021": 4, "2020": 14, "2019": 4, "2018": 4, "2017": 5, "2016": 4, "2015": 9, "2014": 4, "2013": 1, "2012": 5}}, "Universidad Del Pac\u00edfico Ecuador": {"Country": "Ecuador", "Works": {"2025": 2, "2024": 17, "2023": 24, "2022": 6, "2021": 10, "2020": 12, "2019": 10, "2018": 3, "2017": 2, "2016": 5, "2015": 4, "2014": 4, "2013": 0, "2012": 0}}, "Pacific Arts Association": {"Country": "United States", "Works": {"2025": 0, "2024": 4, "2023": 3, "2022": 0, "2021": 26, "2020": 13, "2019": 0, "2018": 0, "2017": 0, "2016": 20, "2015": 3, "2014": 2, "2013": 0, "2012": 0}}, "Flint Community Schools": {"Country": "United States", "Works": {"2025": 0, "2024": 6, "2023": 2, "2022": 2, "2021": 2, "2020": 0, "2019": 0, "2018": 0, "2017": 1, "2016": 3, "2015": 3, "2014": 1, "2013": 2, "2012": 0}}, "Saxon Police Force": {"Country": "Germany", "Works": {"2025": 0, "2024": 0, "2023": 6, "2022": 6, "2021": 10, "2020": 15, "2019": 3, "2018": 3, "2017": 5, "2016": 9, "2015": 5, "2014": 14, "2013": 1, "2012": 0}}, "Instituto Paulista de Ensino e Pesquisa": {"Country": "Brazil", "Works": {"2025": 0, "2024": 5, "2023": 8, "2022": 4, "2021": 13, "2020": 7, "2019": 7, "2018": 8, "2017": 4, "2016": 3, "2015": 10, "2014": 6, "2013": 7, "2012": 6}}, "Centro Universitario Internazionale": {"Country": "Italy", "Works": {"2025": 2, "2024": 7, "2023": 16, "2022": 17, "2021": 10, "2020": 8, "2019": 8, "2018": 12, "2017": 6, "2016": 6, "2015": 6, "2014": 2, "2013": 3, "2012": 1}}, "Tekniska H\u00f6gskolans Studentk\u00e5r": {"Country": "Sweden", "Works": {"2025": 1, "2024": 6, "2023": 2, "2022": 2, "2021": 9, "2020": 10, "2019": 11, "2018": 5, "2017": 9, "2016": 2, "2015": 1, "2014": 3, "2013": 5, "2012": 7}}, "Islamic Azad University, Shahinshahr Branch": {"Country": "Iran", "Works": {"2025": 2, "2024": 7, "2023": 10, "2022": 12, "2021": 11, "2020": 10, "2019": 15, "2018": 12, "2017": 11, "2016": 4, "2015": 8, "2014": 0, "2013": 0, "2012": 1}}, "Alamo Colleges": {"Country": "United States", "Works": {"2025": 2, "2024": 4, "2023": 2, "2022": 3, "2021": 1, "2020": 4, "2019": 4, "2018": 5, "2017": 3, "2016": 2, "2015": 4, "2014": 1, "2013": 4, "2012": 6}}, "Universidad Tecnol\u00f3gica Emiliano Zapata del Estado de Morelos": {"Country": "Mexico", "Works": {"2025": 1, "2024": 11, "2023": 21, "2022": 14, "2021": 7, "2020": 7, "2019": 10, "2018": 10, "2017": 4, "2016": 6, "2015": 4, "2014": 6, "2013": 3}}, "\u00c9cole nationale sup\u00e9rieure de paysage de Versailles": {"Country": "France", "Works": {"2025": 0, "2024": 10, "2023": 3, "2022": 6, "2021": 5, "2020": 9, "2019": 9, "2018": 7, "2017": 4, "2016": 10, "2015": 8, "2014": 3, "2013": 6, "2012": 2}}, "Termez Institute of Engineering and Technology": {"Country": "Uzbekistan", "Works": {"2025": 0, "2024": 13, "2023": 72, "2022": 23}}, "Instituto Superior de Ci\u00eancias da Educa\u00e7\u00e3o da Hu\u00edla": {"Country": "Angola", "Works": {"2025": 3, "2024": 8, "2023": 7, "2022": 14, "2021": 19, "2020": 13, "2019": 8, "2018": 6, "2017": 3, "2016": 2, "2015": 7, "2014": 18}}, "Instituto Tecnol\u00f3gico Superior del Occidente del Estado de Hidalgo": {"Country": "Mexico", "Works": {"2025": 2, "2024": 11, "2023": 15, "2022": 23, "2021": 9, "2020": 7, "2019": 17, "2018": 9, "2017": 6, "2016": 2, "2015": 2, "2014": 1, "2013": 1, "2012": 0}}, "Russian-Tajik Slavonic University": {"Country": "Tajikistan", "Works": {"2025": 1, "2024": 9, "2023": 2, "2022": 14, "2021": 14, "2020": 9, "2019": 12, "2018": 23, "2017": 10, "2016": 3, "2015": 2, "2014": 3, "2013": 1, "2012": 1}}, "Snow College": {"Country": "United States", "Works": {"2025": 3, "2024": 5, "2023": 9, "2022": 10, "2021": 4, "2020": 5, "2019": 6, "2018": 14, "2017": 9, "2016": 4, "2015": 3, "2014": 5, "2013": 1, "2012": 1}}, "Technical College of the Lowcountry": {"Country": "United States", "Works": {"2025": 0, "2024": 2, "2023": 1, "2022": 5, "2021": 4, "2020": 6, "2019": 5, "2018": 8, "2017": 8, "2016": 1, "2015": 1, "2014": 3, "2013": 4, "2012": 2}}, "Harrisburg Area Community College": {"Country": "United States", "Works": {"2025": 0, "2024": 2, "2023": 2, "2022": 6, "2021": 2, "2020": 7, "2019": 3, "2018": 2, "2017": 0, "2016": 1, "2015": 2, "2014": 3, "2013": 4, "2012": 0}}, "Ural Law Institute Russian Ministry of Internal Affairs": {"Country": "Russia", "Works": {"2025": 2, "2024": 14, "2023": 13, "2022": 22, "2021": 29, "2020": 16, "2019": 5, "2018": 2, "2017": 2, "2016": 1, "2014": 1}}, "University of Structural Engineering and Architecture Lyuben Karavelov": {"Country": "Bulgaria", "Works": {"2025": 0, "2024": 7, "2023": 11, "2022": 4, "2021": 14, "2020": 13, "2019": 3, "2018": 5, "2017": 10, "2016": 6, "2015": 5, "2014": 5, "2013": 6, "2012": 2}}, "Nanjing Institute of Mechatronic Technology": {"Country": "China", "Works": {"2025": 1, "2024": 9, "2023": 12, "2022": 10, "2021": 17, "2020": 14, "2019": 6, "2018": 5, "2017": 6, "2016": 2, "2015": 5, "2014": 6, "2013": 4, "2012": 3}}, "Belarusian State Aviation Academy": {"Country": "Belarus", "Works": {"2025": 2, "2024": 4, "2023": 12, "2022": 16, "2021": 23, "2020": 12, "2019": 9, "2018": 2, "2017": 2, "2016": 7, "2015": 2, "2014": 6, "2013": 1, "2012": 0}}, "Police Academy of the Czech Republic in Prague": {"Country": "Czechia", "Works": {"2025": 4, "2024": 12, "2023": 13, "2022": 19, "2021": 3, "2020": 8, "2019": 7, "2018": 6, "2017": 6, "2016": 7, "2015": 5, "2014": 5, "2013": 2, "2012": 1}}, "Edutus University": {"Country": "Hungary", "Works": {"2025": 2, "2024": 7, "2023": 17, "2022": 12, "2021": 19, "2020": 10, "2019": 6, "2018": 3, "2017": 8, "2016": 6, "2015": 2, "2014": 4, "2013": 3, "2012": 0}}, "University of Applied Management Studies": {"Country": "Germany", "Works": {"2025": 0, "2024": 9, "2023": 13, "2022": 16, "2021": 11, "2020": 17, "2019": 10, "2018": 9, "2017": 6, "2016": 5, "2015": 3, "2014": 2, "2013": 0, "2012": 0}}, "Kyungmin University": {"Country": "South Korea", "Works": {"2025": 5, "2024": 12, "2023": 11, "2022": 6, "2021": 7, "2020": 7, "2019": 9, "2018": 9, "2017": 5, "2016": 10, "2015": 0, "2014": 7, "2013": 5, "2012": 6}}, "South African College of Applied Psychology": {"Country": "South Africa", "Works": {"2025": 5, "2024": 3, "2023": 9, "2022": 9, "2021": 11, "2020": 6, "2019": 3, "2018": 2, "2017": 2, "2016": 4, "2015": 1, "2014": 1, "2013": 2, "2012": 1}}, "Washington Glass School": {"Country": "United States", "Works": {"2025": 1, "2024": 0, "2023": 0, "2022": 1, "2021": 3, "2020": 5, "2019": 11, "2018": 7, "2017": 6, "2016": 3, "2015": 1, "2014": 2, "2013": 0, "2012": 1}}, "Danish College of General Practitioners": {"Country": "Denmark", "Works": {"2025": 1, "2024": 1, "2023": 8, "2022": 2, "2021": 8, "2020": 3, "2019": 6, "2018": 5, "2017": 5, "2016": 7, "2015": 4, "2014": 7, "2013": 10, "2012": 6}}, "Manhattan School of Music": {"Country": "United States", "Works": {"2025": 0, "2024": 4, "2023": 2, "2022": 8, "2021": 6, "2020": 6, "2019": 5, "2018": 3, "2017": 3, "2016": 3, "2015": 1, "2014": 4, "2013": 3, "2012": 1}}, "Ark\u0131n Yarat\u0131c\u0131 Sanatlar ve Tasar\u0131m \u00dcniversitesi": {"Country": "Cyprus", "Works": {"2025": 5, "2024": 8, "2023": 23, "2022": 28, "2021": 21, "2020": 11, "2019": 7, "2018": 3, "2017": 1, "2013": 0}}, "Yongcheng Vocational College": {"Country": "China", "Works": {"2025": 0, "2024": 4, "2023": 8, "2022": 10, "2021": 9, "2020": 2, "2019": 2, "2018": 0, "2017": 0, "2016": 3, "2015": 3, "2014": 8, "2013": 6, "2012": 14}}, "Harold Washington College": {"Country": "United States", "Works": {"2025": 1, "2024": 1, "2023": 5, "2022": 2, "2021": 3, "2020": 4, "2019": 16, "2018": 5, "2017": 8, "2016": 2, "2015": 2, "2014": 6, "2013": 4, "2012": 6}}, "Grossmont College": {"Country": "United States", "Works": {"2025": 0, "2024": 1, "2023": 2, "2022": 1, "2021": 2, "2020": 6, "2019": 4, "2018": 2, "2017": 2, "2016": 3, "2015": 5, "2014": 0, "2013": 1, "2012": 3}}, "Hirosaki Gakuin University": {"Country": "Japan", "Works": {"2025": 0, "2024": 6, "2023": 2, "2022": 2, "2021": 3, "2020": 4, "2019": 5, "2018": 5, "2017": 5, "2016": 11, "2015": 6, "2014": 7, "2013": 8, "2012": 7}}, "Barnsley College": {"Country": "United Kingdom", "Works": {"2025": 2, "2024": 2, "2023": 4, "2022": 1, "2021": 1, "2020": 0, "2019": 1, "2018": 1, "2017": 2, "2016": 0, "2015": 1, "2014": 0, "2013": 0, "2012": 0}}, "Hochschule f\u00fcr Grafik und Buchkunst Leipzig": {"Country": "Germany", "Works": {"2025": 0, "2024": 3, "2023": 28, "2022": 29, "2021": 3, "2020": 2, "2019": 4, "2018": 2, "2017": 0, "2016": 3, "2015": 1, "2014": 0, "2013": 0, "2012": 1}}, "Centre for East European and International Studies": {"Country": "Germany", "Works": {"2025": 6, "2024": 13, "2023": 16, "2022": 31, "2021": 14, "2020": 7, "2019": 10, "2018": 4, "2017": 3, "2012": 0}}, "Higher Education Institution Lucia de Brouck\u00e8re": {"Country": "Belgium", "Works": {"2025": 0, "2024": 0, "2023": 2, "2022": 0, "2021": 4, "2020": 3, "2019": 1, "2018": 1, "2017": 3, "2016": 8, "2015": 10, "2014": 10, "2013": 8, "2012": 4}}, "Petrozavodsk State Glazunov Conservatory": {"Country": "Russia", "Works": {"2025": 1, "2024": 23, "2023": 10, "2022": 23, "2021": 15, "2020": 6, "2019": 9, "2018": 4, "2017": 1, "2016": 2, "2015": 1, "2014": 3, "2013": 4}}, "Central European Institute of Technology": {"Country": "Austria", "Works": {"2025": 3, "2024": 6, "2023": 10, "2022": 7, "2021": 4, "2020": 13, "2019": 2, "2018": 6, "2017": 5, "2016": 5, "2015": 4, "2014": 7, "2013": 6, "2012": 3}}, "The Carolinas Center": {"Country": "United States", "Works": {"2025": 0, "2024": 0, "2023": 1, "2022": 2, "2021": 3, "2020": 4, "2019": 3, "2018": 0, "2017": 1, "2016": 3, "2015": 2, "2014": 7, "2013": 5, "2012": 11}}, "Yonezawa Technical High School": {"Country": "Japan", "Works": {"2025": 0, "2024": 1, "2023": 0, "2022": 0, "2021": 8, "2020": 8, "2019": 5, "2018": 7, "2017": 12, "2016": 12, "2015": 15, "2014": 1, "2013": 0, "2012": 0}}, "Parwan University": {"Country": "Afghanistan", "Works": {"2025": 6, "2024": 17, "2023": 30, "2022": 10, "2021": 17, "2020": 10, "2019": 13, "2017": 0, "2016": 0, "2014": 0, "2013": 0}}, "Greenleaf University": {"Country": "United States", "Works": {"2025": 1, "2024": 3, "2023": 4, "2022": 3, "2021": 12, "2020": 6, "2019": 1, "2018": 2, "2017": 0, "2016": 1, "2015": 3, "2014": 2, "2013": 3, "2012": 2}}, "St. Louis Public Schools": {"Country": "United States", "Works": {"2025": 3, "2024": 3, "2023": 2, "2022": 1, "2021": 1, "2020": 1, "2019": 0, "2018": 1, "2017": 6, "2016": 1, "2015": 2, "2014": 1, "2013": 1, "2012": 1}}, "Universidad Privada Sergio Bernales": {"Country": "Peru", "Works": {"2025": 4, "2024": 5, "2023": 13, "2022": 6, "2021": 8, "2020": 11, "2019": 13, "2018": 6, "2017": 7, "2016": 1, "2015": 9, "2014": 5, "2013": 5, "2012": 4}}, "Riga Graduate School of Law": {"Country": "Latvia", "Works": {"2025": 1, "2024": 2, "2023": 3, "2022": 5, "2021": 14, "2020": 11, "2019": 4, "2018": 4, "2017": 5, "2016": 5, "2015": 4, "2014": 17, "2013": 0, "2012": 5}}, "Universitatea Avram Iancu": {"Country": "Romania", "Works": {"2025": 1, "2024": 3, "2023": 3, "2022": 0, "2021": 2, "2020": 5, "2019": 6, "2018": 4, "2017": 7, "2016": 9, "2015": 7, "2014": 5, "2013": 10, "2012": 6}}, "Kansas Wesleyan University": {"Country": "United States", "Works": {"2025": 0, "2024": 2, "2023": 3, "2022": 1, "2021": 9, "2020": 3, "2019": 2, "2018": 0, "2017": 0, "2016": 2, "2015": 2, "2014": 4, "2013": 4, "2012": 2}}, "Dallas County Community College District": {"Country": "United States", "Works": {"2025": 0, "2024": 0, "2023": 1, "2022": 0, "2021": 2, "2020": 4, "2019": 3, "2018": 7, "2017": 4, "2016": 6, "2015": 0, "2014": 6, "2013": 2, "2012": 2}}, "Ateneo de Naga University": {"Country": "Philippines", "Works": {"2025": 2, "2024": 7, "2023": 11, "2022": 16, "2021": 9, "2020": 7, "2019": 10, "2018": 7, "2017": 3, "2016": 7, "2015": 2, "2014": 13, "2013": 2, "2012": 1}}, "Inver Hills Community College": {"Country": "United States", "Works": {"2025": 0, "2024": 2, "2023": 2, "2022": 8, "2021": 6, "2020": 1, "2019": 4, "2018": 4, "2017": 6, "2016": 1, "2015": 4, "2014": 3, "2013": 1, "2012": 2}}, "Dominican House of Studies": {"Country": "United States", "Works": {"2025": 1, "2024": 4, "2023": 5, "2022": 2, "2021": 5, "2020": 5, "2019": 4, "2018": 1, "2017": 1, "2016": 3, "2015": 1, "2014": 3, "2013": 1, "2012": 1}}, "Butte College": {"Country": "United States", "Works": {"2025": 1, "2024": 6, "2023": 1, "2022": 2, "2021": 5, "2020": 3, "2019": 4, "2018": 3, "2017": 2, "2016": 3, "2015": 1, "2014": 2, "2013": 11, "2012": 1}}, "Japan University of Health Sciences": {"Country": "Japan", "Works": {"2025": 5, "2024": 9, "2023": 11, "2022": 23, "2021": 9, "2020": 9, "2019": 19, "2018": 6, "2017": 7, "2016": 5, "2015": 2}}, "Instituto Superior Polit\u00e9cnico de Gaza": {"Country": "Mozambique", "Works": {"2025": 4, "2024": 19, "2023": 17, "2022": 12, "2021": 10, "2020": 12, "2019": 5, "2018": 4, "2017": 2, "2016": 2, "2015": 1, "2014": 1, "2013": 0, "2012": 0}}, "Wake County Public School System": {"Country": "United States", "Works": {"2025": 0, "2024": 5, "2023": 1, "2022": 2, "2021": 4, "2020": 7, "2019": 4, "2018": 7, "2017": 6, "2016": 3, "2015": 12, "2014": 2, "2013": 2, "2012": 2}}, "Universidad de Aconcagua": {"Country": "Chile", "Works": {"2025": 0, "2024": 11, "2023": 12, "2022": 16, "2021": 12, "2020": 3, "2019": 7, "2018": 5, "2017": 4, "2016": 4, "2015": 1, "2014": 10, "2013": 2, "2012": 1}}, "Institute of Chartered Financial Analysts of India University, Jaipur": {"Country": "India", "Works": {"2025": 4, "2024": 12, "2023": 13, "2022": 9, "2021": 12, "2020": 10, "2019": 7, "2018": 8, "2017": 8, "2016": 10, "2015": 1, "2014": 5, "2013": 1, "2012": 0}}, "Naval Academy named after Admiral of the Fleet of the Soviet Union NG Kuznetsov": {"Country": "Russia", "Works": {"2025": 3, "2024": 8, "2023": 8, "2022": 13, "2021": 10, "2020": 10, "2019": 13, "2018": 5, "2017": 5, "2016": 2, "2015": 1, "2014": 2, "2012": 1}}, "Shizuoka Eiwa Gakuin University": {"Country": "Japan", "Works": {"2025": 0, "2024": 1, "2023": 3, "2022": 1, "2021": 2, "2020": 1, "2019": 3, "2018": 1, "2017": 3, "2016": 3, "2015": 2, "2014": 0, "2013": 6, "2012": 5}}, "East Georgia State College": {"Country": "United States", "Works": {"2025": 0, "2024": 1, "2023": 4, "2022": 4, "2021": 9, "2020": 2, "2019": 5, "2018": 10, "2017": 3, "2016": 3, "2015": 5, "2014": 4, "2013": 7, "2012": 7}}, "Dundee and Angus College": {"Country": "United Kingdom", "Works": {"2025": 1, "2024": 4, "2023": 12, "2022": 7, "2021": 7, "2020": 6, "2019": 3, "2018": 3, "2017": 5, "2016": 4, "2015": 6, "2014": 3, "2013": 3, "2012": 0}}, "Quirino State University": {"Country": "Philippines", "Works": {"2025": 2, "2024": 9, "2023": 21, "2022": 24, "2021": 24, "2020": 6, "2019": 6, "2018": 5, "2017": 1, "2016": 3, "2015": 2, "2014": 1}}, "Pennsylvania Institute of Technology": {"Country": "United States", "Works": {"2025": 2, "2024": 3, "2023": 7, "2022": 2, "2021": 4, "2020": 8, "2019": 3, "2018": 3, "2017": 1, "2016": 0, "2015": 1, "2014": 1, "2013": 8, "2012": 2}}, "Humak University of Applied Sciences": {"Country": "Finland", "Works": {"2025": 0, "2024": 10, "2023": 17, "2022": 6, "2021": 8, "2020": 9, "2019": 5, "2018": 5, "2017": 20, "2016": 14, "2015": 2, "2014": 1, "2013": 1, "2012": 0}}, "Tajik State University of Law Business and Politics": {"Country": "Tajikistan", "Works": {"2025": 1, "2024": 9, "2023": 12, "2022": 47, "2021": 12, "2020": 11, "2018": 5, "2017": 2, "2016": 1, "2014": 2, "2013": 1}}, "Vyatka State University of Humanities": {"Country": "Russia", "Works": {"2025": 0, "2024": 0, "2023": 0, "2022": 10, "2021": 10, "2020": 1, "2019": 1, "2018": 0, "2017": 5, "2016": 15, "2015": 20, "2014": 11, "2013": 7, "2012": 9}}, "Volgograd State Academy of Physical Culture": {"Country": "Russia", "Works": {"2025": 2, "2024": 5, "2023": 0, "2022": 17, "2021": 17, "2020": 11, "2019": 8, "2018": 13, "2017": 11, "2016": 8, "2015": 4, "2014": 3, "2013": 1, "2012": 1}}, "College of the Muscogee Nation": {"Country": "United States", "Works": {"2025": 1, "2024": 2, "2023": 1, "2022": 4, "2021": 2, "2020": 0, "2019": 1, "2018": 1, "2017": 0, "2016": 4, "2015": 0, "2014": 2, "2013": 2, "2012": 0}}, "Wilhelm L\u00f6he University for Applied Sciences": {"Country": "Germany", "Works": {"2025": 1, "2024": 8, "2023": 8, "2022": 13, "2021": 7, "2020": 10, "2019": 5, "2018": 15, "2017": 10, "2016": 12, "2015": 7, "2014": 2, "2013": 1, "2012": 1}}, "Pa\u0144stwowa Wy\u017csza Szko\u0142a Zawodowa w Raciborzu": {"Country": "Poland", "Works": {"2025": 0, "2024": 5, "2023": 4, "2022": 5, "2021": 3, "2020": 6, "2019": 11, "2018": 9, "2017": 7, "2016": 13, "2015": 8, "2014": 5, "2013": 5, "2012": 8}}, "Institutul Na\u0163ional de Cercetare-Dezvoltare pentru Mecatronic\u0103 si Tehnica Masur\u0103rii": {"Country": "Romania", "Works": {"2025": 0, "2024": 4, "2023": 9, "2022": 14, "2021": 21, "2020": 11, "2019": 7, "2018": 8, "2017": 4, "2016": 1, "2015": 3, "2014": 1, "2013": 2, "2012": 2}}, "Selangor Business School": {"Country": "Malaysia", "Works": {"2025": 3, "2024": 14, "2023": 9, "2022": 12, "2021": 13, "2020": 7, "2019": 8, "2018": 5, "2017": 3, "2016": 3, "2015": 1, "2014": 4, "2013": 3, "2012": 9}}, "Indian Institute of Information Technology Senapati, Manipur": {"Country": "India", "Works": {"2025": 4, "2024": 14, "2023": 10, "2022": 12, "2021": 17, "2020": 15, "2019": 11, "2018": 12, "2017": 5, "2016": 2, "2015": 2}}, "Ankara M\u00fczik ve G\u00fczel Sanatlar \u00dcniversitesi": {"Country": "T\u00fcrkiye", "Works": {"2025": 11, "2024": 21, "2023": 30, "2022": 13, "2021": 12, "2020": 13, "2019": 1, "2018": 3}}, "Centre R\u00e9gional des M\u00e9tiers de l'\u00c9ducation et de la Formation Casablanca-Settat": {"Country": "Morocco", "Works": {"2025": 8, "2024": 16, "2023": 30, "2022": 14, "2021": 13, "2020": 11, "2019": 4, "2018": 2, "2017": 6}}, "Mesalands Community College": {"Country": "United States", "Works": {"2025": 1, "2024": 7, "2023": 5, "2022": 4, "2021": 8, "2020": 15, "2019": 11, "2018": 4, "2017": 2, "2016": 3, "2015": 2, "2014": 4, "2013": 2, "2012": 3}}, "Goldey\u2013Beacom College": {"Country": "United States", "Works": {"2025": 1, "2024": 8, "2023": 7, "2022": 7, "2021": 9, "2020": 6, "2019": 7, "2018": 6, "2017": 2, "2016": 3, "2015": 4, "2014": 2, "2013": 0, "2012": 0}}, "Antelope Valley College": {"Country": "United States", "Works": {"2025": 0, "2024": 2, "2023": 4, "2022": 2, "2021": 4, "2020": 8, "2019": 3, "2018": 5, "2017": 5, "2016": 2, "2015": 4, "2014": 0, "2013": 4, "2012": 8}}, "Laramie County Community College": {"Country": "United States", "Works": {"2025": 0, "2024": 2, "2023": 14, "2022": 8, "2021": 8, "2020": 4, "2019": 4, "2018": 6, "2017": 4, "2016": 0, "2015": 7, "2014": 4, "2013": 3, "2012": 5}}, "Utah State University Eastern": {"Country": "United States", "Works": {"2025": 1, "2024": 2, "2023": 9, "2022": 5, "2021": 5, "2020": 8, "2019": 10, "2018": 15, "2017": 6, "2016": 4, "2015": 6, "2014": 3, "2013": 3, "2012": 3}}, "Bluegrass Community and Technical College": {"Country": "United States", "Works": {"2025": 1, "2024": 7, "2023": 8, "2022": 7, "2021": 9, "2020": 8, "2019": 10, "2018": 4, "2017": 6, "2016": 5, "2015": 5, "2014": 7, "2013": 4, "2012": 6}}, "Universit\u00e9 Notre Dame d'Ha\u00efti": {"Country": "Haiti", "Works": {"2025": 3, "2024": 13, "2023": 14, "2022": 8, "2021": 10, "2020": 7, "2019": 15, "2018": 3, "2017": 8, "2016": 5, "2015": 6, "2014": 2, "2013": 2, "2012": 1}}, "Universit\u00e9 de Cepromad": {"Country": "DR Congo", "Works": {"2025": 0, "2024": 3, "2023": 6, "2022": 10, "2021": 8, "2020": 4, "2019": 12, "2018": 6, "2017": 4, "2016": 3, "2015": 5, "2014": 6, "2013": 7, "2012": 4}}, "Universitas Tri Dharma": {"Country": "Indonesia", "Works": {"2025": 0, "2024": 2, "2023": 23, "2022": 20, "2021": 17, "2020": 12, "2019": 11, "2018": 6, "2017": 9, "2016": 1, "2014": 1, "2013": 1}}, "Da Vinci Institute": {"Country": "South Africa", "Works": {"2025": 1, "2024": 6, "2023": 7, "2022": 11, "2021": 6, "2020": 19, "2019": 14, "2018": 8, "2017": 1, "2016": 3, "2015": 1, "2014": 1, "2013": 1, "2012": 0}}, "Studix": {"Country": "Norway", "Works": {"2025": 0, "2024": 2, "2023": 9, "2022": 8, "2021": 14, "2020": 5, "2019": 12, "2018": 2, "2017": 8, "2016": 8, "2015": 1, "2014": 6, "2013": 12, "2012": 4}}, "Universidad de Ixtlahuaca CUI": {"Country": "Mexico", "Works": {"2025": 3, "2024": 7, "2023": 18, "2022": 9, "2021": 21, "2020": 13, "2019": 8, "2018": 7, "2017": 4, "2016": 4, "2015": 3, "2013": 1, "2012": 1}}, "Trinity University of Asia": {"Country": "Philippines", "Works": {"2025": 14, "2024": 15, "2023": 8, "2022": 9, "2021": 10, "2020": 7, "2019": 5, "2018": 3, "2017": 0, "2016": 0, "2015": 1, "2014": 0, "2013": 1, "2012": 0}}, "Danang Architecture University": {"Country": "Vietnam", "Works": {"2025": 4, "2024": 15, "2023": 13, "2022": 10, "2021": 26, "2020": 11, "2019": 13, "2018": 7, "2017": 3, "2016": 1}}, "Pasco\u2013Hernando State College": {"Country": "United States", "Works": {"2025": 0, "2024": 1, "2023": 2, "2022": 2, "2021": 0, "2020": 3, "2019": 3, "2018": 10, "2017": 4, "2016": 0, "2015": 0, "2014": 2, "2013": 4, "2012": 0}}, "Escola Secund\u00e1ria Quinta do Marqu\u00eas": {"Country": "Portugal", "Works": {"2025": 1, "2024": 2, "2023": 2, "2022": 2, "2021": 1, "2020": 3, "2019": 2, "2018": 6, "2017": 1, "2016": 6, "2015": 2, "2014": 5, "2013": 3, "2012": 4}}, "Graduate School of Government and European Studies": {"Country": "Slovenia", "Works": {"2025": 0, "2024": 3, "2023": 3, "2022": 7, "2021": 3, "2020": 14, "2019": 10, "2018": 6, "2017": 4, "2016": 10, "2015": 4, "2014": 3, "2013": 2, "2012": 4}}, "Sociedade de Ensino Universit\u00e1rio do Nordeste": {"Country": "Brazil", "Works": {"2025": 1, "2024": 3, "2023": 7, "2022": 5, "2021": 14, "2020": 10, "2019": 7, "2018": 10, "2017": 8, "2016": 9, "2015": 12, "2014": 3, "2013": 4, "2012": 6}}, "Jozjan university": {"Country": "Afghanistan", "Works": {"2025": 7, "2024": 22, "2023": 15, "2022": 6, "2021": 16, "2020": 15, "2019": 13, "2018": 5, "2017": 0, "2016": 2, "2014": 0, "2013": 0}}, "Guilford County Schools": {"Country": "United States", "Works": {"2025": 1, "2024": 6, "2023": 4, "2022": 3, "2021": 19, "2020": 7, "2019": 4, "2018": 1, "2017": 2, "2016": 4, "2015": 0, "2014": 2, "2013": 3, "2012": 3}}, "Krantisinh Nana Patil College of Veterinary Science": {"Country": "India", "Works": {"2025": 0, "2024": 8, "2023": 16, "2022": 19, "2021": 18, "2020": 14, "2019": 2, "2018": 5, "2017": 6, "2016": 4, "2015": 2, "2014": 3, "2013": 4, "2012": 1}}, "Escola Superior de Educa\u00e7\u00e3o de Almeida Garrett": {"Country": "Portugal", "Works": {"2025": 0, "2024": 2, "2023": 9, "2022": 25, "2021": 27, "2020": 12, "2019": 5, "2018": 4, "2017": 2, "2016": 2, "2015": 7, "2014": 3, "2013": 0, "2012": 2}}, "Annapoorana Medical College and Hospitals": {"Country": "India", "Works": {"2025": 0, "2024": 7, "2023": 7, "2022": 6, "2021": 7, "2020": 8, "2019": 7, "2018": 14, "2017": 11, "2016": 18, "2015": 4, "2014": 3, "2013": 5, "2012": 5}}, "Appalachian College of Pharmacy": {"Country": "United States", "Works": {"2025": 1, "2024": 3, "2023": 2, "2022": 2, "2021": 4, "2020": 6, "2019": 7, "2018": 1, "2017": 7, "2016": 3, "2015": 11, "2014": 9, "2013": 9, "2012": 13}}, "University for Peace": {"Country": "The Netherlands", "Works": {"2025": 0, "2024": 2, "2023": 4, "2022": 8, "2021": 2, "2020": 8, "2019": 11, "2018": 3, "2017": 4, "2016": 4, "2015": 10, "2014": 6, "2013": 6, "2012": 2}}, "Hajvery University": {"Country": "Pakistan", "Works": {"2025": 2, "2024": 10, "2023": 12, "2022": 12, "2021": 5, "2020": 8, "2019": 6, "2018": 3, "2017": 9, "2016": 5, "2015": 3, "2014": 1, "2013": 15, "2012": 11}}, "Seibo Jogakuin Junior College": {"Country": "Japan", "Works": {"2025": 0, "2024": 0, "2023": 0, "2022": 2, "2021": 0, "2020": 0, "2019": 0, "2018": 0, "2017": 0, "2016": 0, "2015": 0, "2014": 0, "2013": 0, "2012": 1}}, "Academy of Performing Arts in Prague": {"Country": "Czechia", "Works": {"2025": 0, "2024": 13, "2023": 16, "2022": 12, "2021": 14, "2020": 9, "2019": 7, "2018": 7, "2017": 5, "2016": 6, "2015": 4, "2014": 1, "2013": 0, "2012": 0}}, "Roane State Community College": {"Country": "United States", "Works": {"2025": 0, "2024": 4, "2023": 3, "2022": 0, "2021": 5, "2020": 5, "2019": 5, "2018": 2, "2017": 0, "2016": 5, "2015": 2, "2014": 1, "2013": 2, "2012": 4}}, "Independence Community College": {"Country": "United States", "Works": {"2025": 1, "2024": 4, "2023": 6, "2022": 4, "2021": 7, "2020": 4, "2019": 1, "2018": 2, "2017": 1, "2016": 4, "2015": 2, "2014": 2, "2013": 1, "2012": 4}}, "Tunisia Private University": {"Country": "Tunisia", "Works": {"2025": 1, "2024": 7, "2023": 9, "2022": 13, "2021": 8, "2020": 12, "2019": 8, "2018": 8, "2017": 6, "2016": 6, "2015": 6, "2014": 4, "2013": 1, "2012": 3}}, "University of the Visual & Performing Arts": {"Country": "Sri Lanka", "Works": {"2025": 4, "2024": 7, "2023": 20, "2022": 13, "2021": 10, "2020": 6, "2019": 9, "2018": 5, "2017": 3, "2016": 1, "2015": 4, "2014": 4, "2013": 2, "2012": 4}}, "Northwest Vista College": {"Country": "United States", "Works": {"2025": 1, "2024": 2, "2023": 3, "2022": 6, "2021": 17, "2020": 9, "2019": 6, "2018": 7, "2017": 8, "2016": 2, "2015": 3, "2014": 1, "2013": 7, "2012": 4}}, "Suncheon Jeil College": {"Country": "South Korea", "Works": {"2025": 1, "2024": 3, "2023": 2, "2022": 5, "2021": 10, "2020": 3, "2019": 12, "2018": 18, "2017": 10, "2016": 13, "2015": 7, "2014": 2, "2013": 2, "2012": 4}}, "Texas Tech University System": {"Country": "United States", "Works": {"2025": 8, "2024": 17, "2023": 12, "2022": 17, "2021": 8, "2020": 13, "2019": 1, "2018": 6, "2017": 5, "2016": 2, "2015": 1, "2014": 2, "2013": 1, "2012": 0}}, "Unicorn University": {"Country": "Czechia", "Works": {"2025": 1, "2024": 5, "2023": 3, "2022": 2, "2021": 13, "2020": 11, "2019": 5, "2018": 10, "2017": 8, "2016": 9, "2015": 9, "2014": 4, "2013": 1, "2012": 0}}, "Islamic Azad University, Boukan": {"Country": "Iran", "Works": {"2025": 2, "2024": 13, "2023": 9, "2022": 8, "2021": 3, "2020": 4, "2019": 6, "2018": 6, "2017": 7, "2016": 7, "2015": 11, "2014": 6, "2013": 8, "2012": 4}}, "Wesley J\u00e1nos Lelk\u00e9szk\u00e9pz\u0151 F\u0151iskola": {"Country": "Hungary", "Works": {"2025": 1, "2024": 9, "2023": 29, "2022": 9, "2021": 7, "2020": 3, "2019": 13, "2018": 11, "2017": 6, "2016": 1, "2015": 2, "2014": 2, "2013": 3, "2012": 3}}, "Munger University": {"Country": "India", "Works": {"2025": 3, "2024": 12, "2023": 19, "2022": 26, "2021": 13, "2020": 11, "2019": 4, "2018": 5, "2017": 0, "2016": 0, "2015": 2, "2014": 1}}, "Dwight School": {"Country": "United States", "Works": {"2025": 1, "2024": 1, "2023": 2, "2022": 7, "2021": 2, "2020": 2, "2019": 0, "2018": 2, "2017": 2, "2015": 0, "2014": 1, "2012": 0}}, "Funda\u00e7\u00e3o Educacional D. Andr\u00e9 Arcoverde": {"Country": "Brazil", "Works": {"2025": 0, "2024": 5, "2023": 1, "2022": 2, "2021": 4, "2020": 4, "2019": 12, "2018": 20, "2017": 11, "2016": 5, "2015": 5, "2014": 1, "2013": 1, "2012": 4}}, "Universidad Yacamb\u00fa": {"Country": "Venezuela", "Works": {"2025": 2, "2024": 1, "2023": 10, "2022": 13, "2021": 17, "2020": 9, "2019": 9, "2018": 5, "2017": 4, "2016": 2, "2015": 8, "2014": 3, "2013": 3, "2012": 2}}, "Islamic Azad University of Tafresh": {"Country": "Iran", "Works": {"2025": 0, "2024": 2, "2023": 4, "2022": 4, "2021": 5, "2020": 1, "2019": 5, "2018": 1, "2017": 9, "2016": 10, "2015": 2, "2014": 5, "2013": 4, "2012": 15}}, "Institut Sup\u00e9rieur de Statistique de Lubumbashi": {"Country": "DR Congo", "Works": {"2025": 7, "2024": 9, "2023": 7, "2022": 18, "2021": 4, "2020": 14, "2019": 9, "2018": 10, "2017": 7, "2016": 8, "2015": 4, "2014": 2, "2013": 0, "2012": 1}}, "Edgewood Independent School District": {"Country": "United States", "Works": {"2025": 1, "2024": 4, "2023": 5, "2022": 4, "2021": 5, "2020": 3, "2019": 2, "2018": 3, "2017": 2, "2016": 4, "2015": 3, "2014": 3, "2013": 1, "2012": 1}}, "Universidad Valle del Momboy": {"Country": "Venezuela", "Works": {"2025": 1, "2024": 4, "2023": 1, "2022": 3, "2021": 2, "2020": 1, "2019": 0, "2018": 11, "2017": 5, "2016": 4, "2015": 17, "2014": 19, "2013": 10, "2012": 0}}, "Universidad Aeron\u00e1utica en Quer\u00e9taro": {"Country": "Mexico", "Works": {"2025": 2, "2024": 13, "2023": 11, "2022": 7, "2021": 14, "2020": 4, "2019": 11, "2018": 13, "2017": 5, "2016": 13, "2015": 4, "2014": 1, "2013": 1, "2012": 2}}, "Madan Bhandari Academy of Health Sciences": {"Country": "Nepal", "Works": {"2025": 11, "2024": 28, "2023": 32, "2022": 16, "2021": 13, "2020": 3}}, "HMU Potsdam \u2013 Health and Medical University Potsdam": {"Country": "Germany", "Works": {"2025": 5, "2024": 34, "2023": 29, "2022": 18, "2021": 11, "2020": 5}}, "Orlando College of Osteopathic Medicine": {"Country": "United States", "Works": {"2025": 23, "2024": 72, "2023": 6, "2022": 1, "2019": 0}}, "University of Maine at Fort Kent": {"Country": "United States", "Works": {"2025": 0, "2024": 7, "2023": 5, "2022": 3, "2021": 10, "2020": 9, "2019": 2, "2018": 10, "2017": 5, "2016": 5, "2015": 2, "2014": 3, "2013": 5, "2012": 3}}, "Swiss Hotel Management School": {"Country": "Switzerland", "Works": {"2025": 1, "2024": 1, "2023": 3, "2022": 11, "2021": 3, "2020": 12, "2019": 16, "2018": 2, "2017": 2, "2016": 3, "2015": 5, "2014": 2, "2013": 3, "2012": 6}}, "Kharkiv University of Humanities People\u2019s Ukrainian Academy": {"Country": "Ukraine", "Works": {"2025": 0, "2024": 6, "2023": 11, "2022": 10, "2021": 14, "2020": 11, "2019": 10, "2018": 8, "2017": 7, "2016": 2, "2015": 4, "2014": 2, "2013": 2, "2012": 2}}, "Uganda Technology and Management University": {"Country": "Uganda", "Works": {"2025": 0, "2024": 4, "2023": 4, "2022": 4, "2021": 9, "2020": 10, "2019": 12, "2018": 18, "2017": 9, "2016": 11, "2015": 8, "2014": 5, "2013": 7}}, "Bamenda University of Science and Technology": {"Country": "Cameroon", "Works": {"2025": 2, "2024": 7, "2023": 11, "2022": 14, "2021": 9, "2020": 15, "2019": 6, "2018": 5, "2017": 5, "2016": 7, "2015": 3, "2014": 9, "2013": 2, "2012": 4}}, "Sorabol College": {"Country": "South Korea", "Works": {"2025": 0, "2024": 0, "2023": 3, "2022": 4, "2021": 1, "2020": 3, "2019": 1, "2018": 5, "2017": 4, "2016": 4, "2015": 12, "2014": 9, "2013": 6, "2012": 6}}, "\u00c9cole Sup\u00e9rieure d'Ing\u00e9nieurs des Travaux de la Construction de Metz": {"Country": "France", "Works": {"2025": 0, "2024": 11, "2023": 13, "2022": 12, "2021": 15, "2020": 14, "2019": 10, "2018": 3, "2017": 7, "2016": 8, "2015": 0, "2014": 2, "2013": 1, "2012": 1}}, "Batken State University": {"Country": "Kyrgyzstan", "Works": {"2025": 10, "2024": 1, "2023": 22, "2022": 14, "2021": 24, "2020": 6, "2019": 16, "2018": 2, "2017": 5, "2016": 0, "2015": 0, "2013": 1}}, "Universidad del Valle de Guadiana": {"Country": "Mexico", "Works": {"2025": 0, "2024": 7, "2023": 8, "2022": 12, "2021": 9, "2020": 20, "2019": 11, "2018": 10, "2017": 6, "2016": 2, "2015": 1, "2014": 2, "2013": 3, "2012": 2}}, "Cracow School of Health Promotion": {"Country": "Poland", "Works": {"2025": 5, "2024": 3, "2023": 4, "2022": 7, "2021": 2, "2020": 7, "2019": 7, "2018": 7, "2017": 15, "2016": 8, "2015": 10, "2014": 7, "2013": 4, "2012": 4}}, "Rostov State Rakhmaninov Conservatory": {"Country": "Russia", "Works": {"2025": 1, "2024": 5, "2023": 8, "2022": 28, "2021": 28, "2020": 4, "2019": 1, "2018": 1, "2016": 1, "2015": 3, "2014": 7, "2013": 11, "2012": 2}}, "Association for Core Texts and Courses": {"Country": "United States", "Works": {"2025": 0, "2024": 0, "2023": 1, "2022": 0, "2021": 1, "2020": 1, "2019": 1, "2018": 0, "2017": 1, "2016": 3, "2015": 4, "2014": 2, "2013": 0, "2012": 4}}, "Center for the Study of Community Colleges": {"Country": "United States", "Works": {"2024": 0, "2023": 0, "2022": 1, "2021": 0, "2020": 0, "2019": 0, "2018": 1, "2017": 1, "2016": 5, "2015": 1, "2014": 1, "2013": 0, "2012": 4}}, "Osaka Prefectural Makino high school": {"Country": "Japan", "Works": {"2025": 0, "2024": 1, "2023": 0, "2022": 0, "2021": 0, "2020": 1, "2019": 1, "2018": 0, "2017": 2, "2016": 2, "2015": 0, "2014": 0, "2013": 1, "2012": 0}}, "Kendriya Vidyalaya Sangathan": {"Country": "India", "Works": {"2025": 1, "2024": 7, "2023": 11, "2022": 15, "2021": 10, "2020": 11, "2019": 3, "2018": 5, "2017": 10, "2016": 8, "2015": 7, "2014": 1, "2013": 2, "2012": 2}}, "Akademia Nauk Stosowanych w Wa\u0142cz": {"Country": "Poland", "Works": {"2025": 0, "2024": 6, "2023": 0, "2022": 0, "2021": 2, "2020": 3, "2019": 6, "2018": 15, "2017": 10, "2016": 6, "2015": 2, "2014": 10, "2013": 1, "2012": 6}}, "Local Government Training Institute": {"Country": "Tanzania", "Works": {"2025": 6, "2024": 25, "2023": 18, "2022": 14, "2021": 6, "2020": 21, "2019": 0, "2018": 2, "2017": 0, "2016": 1, "2015": 3, "2014": 5}}, "Netrokona University": {"Country": "Bangladesh", "Works": {"2025": 4, "2024": 39, "2023": 25, "2022": 19, "2021": 13, "2020": 0, "2015": 0}}, "Shizuoka University of Art and Culture": {"Country": "Japan", "Works": {"2025": 4, "2024": 1, "2023": 0, "2022": 7, "2021": 1, "2020": 7, "2019": 6, "2018": 9, "2017": 3, "2016": 6, "2015": 6, "2014": 4, "2013": 7, "2012": 8}}}