{"Fhrai Institute of Hospitality Management": {"Country": "India", "Works": {"2024": 2}}, "Fundaci\u00f3n Universidad Empresa de la Regi\u00f3n de Murcia": {"Country": "Spain", "Works": {"2025": 0, "2024": 0, "2022": 0, "2021": 0, "2020": 0, "2019": 0, "2018": 0, "2017": 0, "2016": 0, "2015": 1, "2014": 0, "2013": 1}}, "Namgyal Tantric College": {"Country": "India", "Works": {"2024": 0, "2023": 0, "2022": 0, "2021": 0, "2020": 0, "2019": 1, "2018": 0, "2017": 0, "2016": 0, "2015": 0, "2014": 0, "2013": 0, "2012": 0}}, "Universidad Tollancingo": {"Country": "Mexico", "Works": {"2022": 0, "2020": 0, "2019": 0, "2018": 1, "2017": 1}}, "Motosu Shoyo High School": {"Country": "Japan", "Works": {"2025": 1, "2024": 0, "2023": 0, "2022": 0, "2021": 0, "2020": 0, "2019": 0, "2018": 0, "2017": 0, "2016": 0, "2015": 0, "2014": 0, "2013": 0, "2012": 0}}, "Orio Aishin Junior College": {"Country": "Japan", "Works": {"2018": 0}}, "Aichi Prefectural Kasugai Higashi High School": {"Country": "Japan", "Works": {"2023": 0, "2022": 0, "2021": 1, "2020": 0, "2019": 0, "2018": 0, "2017": 0, "2016": 0, "2015": 0, "2014": 0, "2013": 0, "2012": 0}}, "Klaip\u0117dos Verslo Auk\u0161toji Mokykla": {"Country": "Lithuania", "Works": {"2025": 0, "2021": 1, "2020": 1}}, "Our School at Blair Grocery": {"Country": "United States", "Works": {"2025": 0, "2024": 0, "2023": 0, "2022": 0, "2021": 0, "2020": 0, "2018": 0, "2017": 0, "2016": 0, "2015": 0, "2014": 0, "2013": 0, "2012": 0}}, "Mie Prefectural Kobe High School": {"Country": "Japan", "Works": {"2022": 0, "2019": 1}}, "Aichi Prefectural Toyohashi School for the Deaf": {"Country": "Japan", "Works": {"2024": 0, "2023": 0, "2022": 0, "2021": 0, "2019": 1, "2016": 0, "2013": 0}}, "Mfantsiman Girls Secondary School": {"Country": "Ghana", "Works": {"2024": 1, "2022": 1}}, "ZD Kr\u00e1sn\u00e1 Hora Nad Vltavou (Czechia)": {"Country": "Czechia", "Works": {"2025": 0, "2024": 0, "2023": 0, "2022": 0, "2021": 0, "2020": 1, "2014": 0}}, "Sunny Days Learning Center of Stickney": {"Country": "United States", "Works": {}}, "Universidad Privada de Irapuato": {"Country": "Mexico", "Works": {"2024": 1, "2023": 0, "2022": 0, "2021": 0, "2019": 0, "2017": 0, "2016": 1}}, "Fukui Prefectural Maruoka High School": {"Country": "Japan", "Works": {"2025": 0, "2024": 0, "2023": 0, "2021": 0, "2018": 0, "2017": 0, "2016": 0, "2015": 0, "2014": 0, "2013": 0, "2012": 0}}, "Reid State Technical College": {"Country": "United States", "Works": {"2014": 0}}, "Hvorfor det": {"Country": "Norway", "Works": {}}, "Kanagawa Prefectural Odawara Johoku Technical High School": {"Country": "Japan", "Works": {}}, "New Jersey Community College Consortium For Workforce & Economic Development": {"Country": "United States", "Works": {"2023": 0, "2018": 0, "2017": 0, "2016": 0, "2015": 1, "2014": 0, "2013": 0, "2012": 0}}, "Florida International University Alumni Association": {"Country": "United States", "Works": {"2025": 0, "2024": 0, "2023": 0, "2022": 0, "2021": 0, "2020": 2}}, "Kawasaki Univ Yato Elementary School": {"Country": "Japan", "Works": {"2017": 1}}, "Nagano Prefectural Board of Education": {"Country": "Japan", "Works": {"2018": 0, "2017": 0, "2016": 0, "2015": 1, "2014": 0, "2012": 0}}, "Universidad Isidro Fabela de Toluca": {"Country": "Mexico", "Works": {"2025": 2}}, "Liceo Jubilar Juan Pablo II": {"Country": "Uruguay", "Works": {"2018": 0, "2015": 0, "2014": 0, "2012": 0}}, "Great Plains College": {"Country": "Canada", "Works": {"2019": 0, "2013": 0}}, "Don Law Institute": {"Country": "Russia", "Works": {"2023": 1, "2021": 0}}, "Blueberry Academy": {"Country": "United Kingdom", "Works": {"2015": 1}}, "Hakodate Clinical Welfare College": {"Country": "Japan", "Works": {"2025": 0, "2024": 0, "2023": 0, "2022": 0, "2021": 1, "2017": 0, "2016": 0, "2015": 0, "2014": 0, "2013": 0, "2012": 0}}, "Conservatorio di Musica Nino Rota": {"Country": "Italy", "Works": {"2015": 1}}, "Elizabeth City Pasquotank Public Schools": {"Country": "United States", "Works": {"2025": 0, "2021": 0, "2020": 1}}, "Institut sup\u00e9rieur de la Magistrature": {"Country": "Morocco", "Works": {"2019": 0, "2018": 0, "2017": 0, "2016": 1, "2013": 1}}, "Tsutsujigaoka Elementary School": {"Country": "Japan", "Works": {"2017": 2}}, "Higher Institute of Islamic Studies": {"Country": "Egypt", "Works": {"2024": 1, "2023": 1}}, "Carthage Central School District": {"Country": "United States", "Works": {"2022": 1, "2021": 1}}, "Orot Israel College": {"Country": "Palestine", "Works": {"2025": 1, "2023": 0, "2019": 1, "2016": 0}}, "Czech Society for Oriental Studies": {"Country": "Czechia", "Works": {"2014": 1}}, "Corporaci\u00f3n John F. Kennedy": {"Country": "Colombia", "Works": {"2023": 0, "2018": 2}}, "Conservatory of Vicenza": {"Country": "Italy", "Works": {"2022": 1, "2019": 0, "2016": 1}}, "Palucca Hochschule f\u00fcr Tanz Dresden": {"Country": "Germany", "Works": {"2024": 1, "2023": 0, "2022": 0, "2021": 0, "2020": 0, "2019": 0, "2018": 1}}, "International Medical And Welfare College Nanao School": {"Country": "Japan", "Works": {"2021": 0, "2014": 0, "2013": 0}}, "Departementssekretariat Schul- und Sportdepartement": {"Country": "Switzerland", "Works": {"2021": 0, "2017": 1}}, "African Bible University": {"Country": "Uganda", "Works": {"2024": 1, "2023": 0, "2022": 0, "2020": 0, "2015": 1}}, "Achievement School District": {"Country": "United States", "Works": {"2025": 0, "2024": 0, "2023": 0, "2022": 0, "2021": 0, "2020": 0, "2019": 1, "2018": 0, "2017": 0, "2016": 0, "2015": 0, "2014": 0, "2013": 0, "2012": 0}}, "Van Xuan University of Technology": {"Country": "Vietnam", "Works": {"2022": 0, "2019": 0, "2018": 0, "2015": 0, "2013": 0}}, "Art Institute of Houston": {"Country": "United States", "Works": {}}, "Funda\u00e7\u00e3o Raquel e Martin Sain": {"Country": "Portugal", "Works": {"2021": 0, "2017": 0, "2016": 0, "2015": 1}}, "Tobu College of Medical Technology": {"Country": "Japan", "Works": {"2023": 1, "2020": 0, "2014": 1}}, "Canadian College of Massage and Hydrotherapy": {"Country": "Canada", "Works": {"2024": 1, "2023": 0, "2022": 0, "2019": 0, "2017": 0, "2016": 0, "2014": 0, "2012": 0}}, "Instituto Profesional Diego Portales": {"Country": "Chile", "Works": {"2024": 0, "2023": 0, "2022": 0, "2021": 0, "2020": 0, "2019": 0, "2018": 0, "2017": 0, "2013": 1}}, "Environmental Construction College": {"Country": "Japan", "Works": {"2024": 0, "2019": 0, "2014": 1}}, "SRH Hochschule f\u00fcr Logistik und Wirtschaft": {"Country": "Germany", "Works": {"2016": 1, "2013": 1}}, "South Georgia Technical College": {"Country": "United States", "Works": {"2024": 0, "2023": 0, "2022": 0, "2021": 0, "2020": 0, "2018": 0, "2017": 0, "2016": 0, "2015": 0, "2014": 0, "2013": 0, "2012": 1}}, "Kismayo University": {"Country": "Somalia", "Works": {"2024": 1, "2023": 1}}, "Instituto Profesional La Araucana": {"Country": "Chile", "Works": {"2024": 0, "2023": 1, "2022": 1}}, "Federation of Busan Science and Technology": {"Country": "South Korea", "Works": {"2025": 0, "2024": 0, "2023": 0, "2022": 0, "2021": 0, "2020": 0, "2019": 1, "2016": 1}}, "California FarmLink": {"Country": "United States", "Works": {"2025": 0, "2024": 0, "2023": 0, "2022": 0, "2021": 0, "2020": 0, "2019": 2, "2016": 0}}, "Orkhon University": {"Country": "Mongolia", "Works": {"2024": 1, "2019": 1}}, "Chhandam School of Kathak": {"Country": "United States", "Works": {"2024": 0, "2022": 0, "2019": 1, "2014": 0, "2013": 0}}, "Southeastern Baptist College": {"Country": "United States", "Works": {"2017": 1}}, "Dechinta Bush University Centre for Research and Learning": {"Country": "Canada", "Works": {"2025": 0, "2024": 0, "2023": 0, "2022": 0, "2021": 1, "2020": 1}}, "Zemaitija College": {"Country": "Lithuania", "Works": {"2024": 0, "2023": 0, "2021": 1, "2018": 0, "2012": 1}}, "Universidad Tecnol\u00f3gica Iberoamericana": {"Country": "Mexico", "Works": {"2020": 1, "2019": 1}}, "Taft University System": {"Country": "United States", "Works": {"2016": 1}}, "National Alliance of Black School Educators": {"Country": "United States", "Works": {"2025": 0, "2024": 0, "2023": 0, "2022": 0, "2021": 0, "2020": 0, "2019": 0, "2018": 0, "2017": 0, "2016": 0, "2015": 0, "2014": 0, "2013": 2, "2012": 0}}, "Universidad Metropolitana del Centro": {"Country": "Mexico", "Works": {"2023": 1, "2020": 1}}, "\u00c9cole des Hautes \u00c9tudes Commerciales Techniques et Informatiques": {"Country": "Morocco", "Works": {"2025": 0, "2024": 1, "2023": 0, "2022": 0, "2021": 0, "2020": 1}}, "Inagakuen Public High School": {"Country": "Japan", "Works": {"2024": 0, "2023": 0, "2016": 1}}, "\u0160olski Center Postojna": {"Country": "Slovenia", "Works": {"2022": 1, "2017": 0}}, "Universidad Estatal de Estudios Pedag\u00f3gicos": {"Country": "Mexico", "Works": {"2025": 1, "2024": 1}}, "Wy\u017csza Szko\u0142a Komunikowania i Medi\u00f3w Spo\u0142ecznych im. Jerzego Giedroycia": {"Country": "Poland", "Works": {}}, "Hauppauge Public School": {"Country": "United States", "Works": {}}, "The School of Visual Theatre": {"Country": "Israel", "Works": {"2022": 0, "2020": 0, "2018": 1}}, "Vi\u0161ja Strokovna \u0160ola za Gostinstvo in Turizem Maribor": {"Country": "Slovenia", "Works": {"2024": 1, "2022": 1}}, "Davis College - Ohio": {"Country": "United States", "Works": {"2023": 0, "2021": 0, "2020": 0, "2019": 0, "2018": 0, "2016": 0, "2015": 0, "2014": 0, "2012": 0}}, "Kyoto Municipal Fushimi Technical High School": {"Country": "Japan", "Works": {"2024": 0, "2022": 0, "2021": 0, "2020": 0, "2019": 1, "2018": 0, "2016": 0, "2013": 0}}, "New York Institute of Art and Design": {"Country": "United States", "Works": {"2024": 1, "2018": 0, "2014": 0, "2012": 1}}, "Merrell University of Beauty Arts and Science": {"Country": "United States", "Works": {"2020": 0, "2012": 0}}, "Etobicoke School of the Arts": {"Country": "Canada", "Works": {"2024": 0, "2023": 1, "2016": 0, "2012": 0}}, "Williams Unified School District": {"Country": "United States", "Works": {"2023": 1}}, "Fakultet za Mediteranske Poslovne Studije": {"Country": "Montenegro", "Works": {"2023": 1, "2015": 1}}, "Oak Field School and Sports College": {"Country": "United Kingdom", "Works": {"2023": 0, "2022": 0, "2021": 0, "2020": 0, "2019": 0, "2018": 0, "2017": 0, "2015": 0, "2014": 2}}, "Accademia di Belle Arti di Foggia": {"Country": "Italy", "Works": {"2018": 1, "2016": 1}}, "Katanga Methodist University": {"Country": "DR Congo", "Works": {"2023": 1, "2017": 1}}, "Dillard Academy": {"Country": "United States", "Works": {"2025": 1, "2023": 0, "2022": 0, "2021": 0, "2020": 0, "2018": 0, "2017": 0, "2016": 0, "2014": 0, "2013": 0, "2012": 0}}, "Board of Education Mino Education Office": {"Country": "Japan", "Works": {"2023": 0, "2022": 1, "2021": 0, "2019": 0, "2016": 0, "2015": 0, "2013": 1}}, "Ibaraki Prefectural Mito First High School": {"Country": "Japan", "Works": {"2018": 1, "2017": 1}}, "Aichi Prefectural Jishukan Senior High School": {"Country": "Japan", "Works": {"2019": 0, "2014": 1}}, "Diagnostick\u00fd \u00dastav pro Ml\u00e1de\u017e": {"Country": "Czechia", "Works": {"2025": 0, "2022": 0, "2017": 2}}, "Universidad Cuauhn\u00e1huac": {"Country": "Mexico", "Works": {"2023": 0, "2022": 0, "2021": 0, "2020": 0, "2019": 0, "2016": 0, "2015": 0, "2014": 0, "2013": 0, "2012": 0}}, "Open Acting Academy": {"Country": "Austria", "Works": {"2023": 0, "2022": 0, "2019": 1, "2017": 0, "2016": 0, "2015": 0, "2014": 0, "2013": 0}}, "International Institute of Business Education": {"Country": "Russia", "Works": {"2025": 0, "2024": 1, "2016": 1}}, "Nenets Agro-Economic College": {"Country": "Russia", "Works": {"2025": 0, "2024": 0, "2023": 0, "2022": 0, "2021": 0, "2020": 0, "2019": 0, "2018": 1, "2017": 1}}, "Fukushima Prefectural Aizu Technical High School": {"Country": "Japan", "Works": {}}, "Universidad Albert Einstein": {"Country": "El Salvador", "Works": {"2023": 0, "2021": 0, "2020": 0, "2019": 1, "2017": 0, "2016": 0, "2015": 0, "2014": 0, "2013": 0, "2012": 0}}, "College of Metaphysical Studies": {"Country": "United States", "Works": {"2023": 1}}, "Kanagawa Prefectural Zushi High School": {"Country": "Japan", "Works": {"2023": 0, "2022": 0, "2021": 0, "2018": 1, "2016": 0, "2015": 0}}, "Trace Crossings Elementary School": {"Country": "United States", "Works": {"2012": 0}}, "Labyrinth Musical Workshop": {"Country": "Greece", "Works": {"2025": 0, "2024": 0, "2023": 1, "2022": 0, "2021": 0, "2020": 0, "2019": 1}}, "Okayama University of Commerce Attached high School": {"Country": "Japan", "Works": {}}, "Ural Institute of Business": {"Country": "Russia", "Works": {"2024": 0, "2020": 0, "2016": 2}}, "\u00c9cole Sup\u00e9rieure des Arts du Cirque": {"Country": "Belgium", "Works": {"2025": 0, "2024": 0, "2023": 0, "2022": 0, "2021": 0, "2020": 0, "2019": 0, "2017": 1, "2016": 1}}, "Mie Prefectural Yokkaichi Technical High School": {"Country": "Japan", "Works": {}}, "National Gugak Center": {"Country": "South Korea", "Works": {"2023": 1, "2021": 0, "2019": 0, "2015": 1}}, "Babble Tree": {"Country": "United States", "Works": {"2020": 0, "2019": 1, "2017": 0}}, "ITESCIA": {"Country": "France", "Works": {"2021": 2}}, "\u00c9cole des Avocats Rh\u00f4ne-Alpes": {"Country": "France", "Works": {"2023": 2}}, "Talmudic University": {"Country": "United States", "Works": {}}, "Sanjo Municipal Tsukioka Elementary School": {"Country": "Japan", "Works": {"2024": 1, "2023": 1}}, "Sunderby Folkh\u00f6gskola": {"Country": "Sweden", "Works": {"2015": 1, "2013": 1}}, "Europejska Akademia Sztuk w Warszawie": {"Country": "Poland", "Works": {}}, "Ohio Association of Community Colleges": {"Country": "United States", "Works": {"2023": 1, "2019": 0, "2017": 0}}, "Public School Forum of North Carolina": {"Country": "United States", "Works": {"2025": 0, "2024": 0, "2023": 0, "2022": 0, "2021": 0, "2020": 0, "2019": 1}}, "Conservatorio di Musica Ottorino Respighi": {"Country": "Italy", "Works": {"2021": 1}}, "Webster University Orlando": {"Country": "United States", "Works": {"2017": 0, "2016": 0, "2014": 0, "2013": 1}}, "German University Association of Advanced Graduate Training": {"Country": "Germany", "Works": {}}, "Asia Life University": {"Country": "South Korea", "Works": {"2024": 0, "2021": 0, "2020": 0, "2017": 1, "2016": 1}}, "Montessori Education Center of the Rockies": {"Country": "United States", "Works": {"2025": 1, "2022": 1}}, "Kantonsschule Rychenberg": {"Country": "Switzerland", "Works": {"2024": 0, "2020": 1}}, "\u00c9cole des Hautes \u00c9tudes en Ing\u00e9nierie des Syst\u00e8mes d'Information": {"Country": "Morocco", "Works": {"2025": 0, "2024": 1, "2023": 0, "2022": 1}}, "Language Systems International College of English": {"Country": "United States", "Works": {"2025": 0, "2024": 0, "2023": 1, "2022": 1}}, "University John of the Cross": {"Country": "Costa Rica", "Works": {"2024": 2}}, "Graham A. Barden Elementary School": {"Country": "United States", "Works": {"2024": 0, "2022": 0, "2020": 0, "2012": 1}}, "Our Lady Academy of Sakura": {"Country": "Japan", "Works": {"2024": 0, "2017": 0, "2016": 0, "2015": 0, "2014": 0, "2013": 0, "2012": 0}}, "National Telford Institute": {"Country": "United Kingdom", "Works": {"2023": 0, "2022": 0, "2021": 0, "2020": 0, "2019": 0, "2018": 0, "2017": 0, "2016": 0, "2015": 2}}, "University of Tifariti": {"Country": "Western Sahara", "Works": {"2025": 0, "2024": 0, "2023": 0, "2022": 0, "2021": 1, "2020": 1}}, "Universidad Real\u00edstica de M\u00e9xico": {"Country": "Mexico", "Works": {"2025": 0, "2024": 0, "2023": 1, "2021": 1}}, "Tver Institute of Ecology and Law": {"Country": "Russia", "Works": {"2025": 0, "2024": 0, "2022": 0, "2021": 0, "2016": 1, "2014": 1}}, "Huntsville Bible College": {"Country": "United States", "Works": {"2024": 1}}, "Academy of Film & Multimedia \u201cMARUBI\u201d": {"Country": "Albania", "Works": {"2023": 0, "2022": 0, "2021": 1, "2012": 1}}, "Tennessee College of Applied Technology": {"Country": "United States", "Works": {"2025": 1, "2022": 0, "2021": 1}}, "Universidad Dominicana Organizaci\u00f3n & M\u00e9todos": {"Country": "Dominican Republic", "Works": {"2025": 0, "2024": 0, "2023": 0, "2022": 0, "2021": 0, "2020": 1, "2019": 0, "2018": 0, "2017": 0, "2016": 0, "2015": 0, "2014": 0, "2013": 0, "2012": 0}}, "Saitama Prefectural Toyooka High School": {"Country": "Japan", "Works": {"2020": 1, "2016": 0, "2012": 0}}, "State Academy of Arts of Turkmenistan": {"Country": "Turkmenistan", "Works": {"2022": 2}}, "Centro Universitario De Integracion Humanistico": {"Country": "Mexico", "Works": {"2020": 0, "2019": 0, "2017": 0, "2012": 1}}, "School for Compassionate Action": {"Country": "United States", "Works": {"2025": 1, "2024": 0, "2023": 0, "2022": 0, "2021": 0, "2020": 0, "2019": 1}}, "Universidad St. John's": {"Country": "Mexico", "Works": {"2022": 0, "2021": 0, "2020": 0, "2016": 0, "2015": 0, "2014": 0, "2012": 2}}, "International Business College - Indianapolis": {"Country": "United States", "Works": {"2025": 0, "2024": 0, "2023": 0, "2022": 0, "2021": 0, "2020": 0, "2019": 2}}, "Gesch\u00e4ftsstelle SVIAL": {"Country": "Switzerland", "Works": {"2014": 1}}, "Academia Rerum Civilium - Vysok\u00e1 Skola Politick\u00fdch a Spole\u010densk\u00fdch V\u011bd": {"Country": "Czechia", "Works": {"2022": 0, "2016": 1, "2015": 1}}, "Laguna Department of Education": {"Country": "United States", "Works": {"2024": 0, "2022": 1, "2020": 1}}, "Capital Academy of Finance and Humanities": {"Country": "Russia", "Works": {"2020": 0, "2017": 1, "2015": 1}}, "Universit\u00e9 William Booth": {"Country": "DR Congo", "Works": {"2024": 1}}, "Conservatorio di Musica di Perugia": {"Country": "Italy", "Works": {"2024": 1, "2020": 0, "2014": 0, "2012": 0}}, "Missouri State University Branch Campus Dalian": {"Country": "China", "Works": {"2024": 0, "2023": 1, "2022": 0, "2017": 0, "2016": 0, "2015": 0, "2014": 0, "2013": 0, "2012": 0}}, "Experimental Security University": {"Country": "Venezuela", "Works": {}}, "Instituto Universitario Centro de Docencia, Investigaci\u00f3n e Informaci\u00f3n en Aprendizaje": {"Country": "Uruguay", "Works": {"2024": 0, "2023": 0, "2022": 1, "2021": 1}}, "South African School of Motion Picture Medium and Live Performance": {"Country": "South Africa", "Works": {"2021": 0, "2016": 0, "2014": 1, "2013": 0}}, "Newpark Music Centre": {"Country": "Ireland", "Works": {"2025": 0, "2024": 0, "2023": 0, "2022": 1, "2018": 1}}, "Universidad del Arte Ganexa": {"Country": "Panama", "Works": {"2023": 1, "2021": 1}}, "Ex'pression College for Digital Arts": {"Country": "United States", "Works": {}}, "Jan Albrecht Music and Art Academy": {"Country": "Slovakia", "Works": {"2023": 0, "2021": 1}}, "Universidad de Negocios ISEC": {"Country": "Mexico", "Works": {"2023": 0, "2022": 1, "2015": 0}}, "Northcentral Arkansas Education Cooperative": {"Country": "United States", "Works": {"2016": 1}}, "International East-European University": {"Country": "Russia", "Works": {"2024": 2}}, "U SPORTS": {"Country": "Canada", "Works": {"2025": 0, "2024": 0, "2023": 0, "2022": 0, "2021": 0, "2020": 0, "2019": 1, "2018": 0, "2017": 0, "2016": 0, "2015": 0, "2014": 0, "2013": 0, "2012": 0}}, "Saint Mary's Academy and College": {"Country": "United States", "Works": {}}, "Pfeiffer University at Charlotte": {"Country": "United States", "Works": {"2025": 0, "2022": 0, "2019": 0, "2018": 0, "2017": 1, "2016": 0}}, "Government Polytechnic College, Rajkot": {"Country": "India", "Works": {"2023": 1, "2019": 1}}, "Higher Institute of Engineering and Technology - King Marriott": {"Country": "Egypt", "Works": {"2025": 0, "2023": 0, "2022": 0, "2021": 1, "2018": 1}}, "\u00c9cole nationale sup\u00e9rieure d'arts de Paris-Cergy": {"Country": "France", "Works": {"2019": 1, "2017": 1}}, "L.E. Fletcher Technical Community College": {"Country": "United States", "Works": {"2024": 0, "2023": 0, "2022": 1, "2020": 0, "2017": 1}}, "Escuela Superior de Comercio Manuel Belgrano": {"Country": "Argentina", "Works": {"2012": 2}}, "\u00c9cole Nationale Sup\u00e9rieure des Postes et des T\u00e9l\u00e9communications": {"Country": "Cameroon", "Works": {"2018": 0, "2017": 0}}, "International College of Management and Sports": {"Country": "Malaysia", "Works": {"2024": 0, "2023": 0, "2021": 0, "2020": 1, "2019": 0, "2017": 0, "2016": 0, "2015": 0, "2014": 0, "2013": 0}}, "Vereinigung \u00d6sterreichischer Bibliothekarinnen und Bibliothekare": {"Country": "Austria", "Works": {"2021": 1, "2020": 1}}, "C\u00e9gep G\u00e9rald-Godin": {"Country": "Canada", "Works": {"2018": 1, "2015": 1}}, "Tecnol\u00f3gico Nacional de M\u00e9xico Campus Canc\u00fan": {"Country": "Mexico", "Works": {"2024": 1, "2021": 1}}, "Instituto Tecnol\u00f3gico Superior de Cananea": {"Country": "Mexico", "Works": {"2016": 1}}, "Deutsche Film- und Fernsehakademie Berlin": {"Country": "Germany", "Works": {"2024": 1, "2020": 1}}, "Yunnan Key Laboratory of Gastrodia Elata and Fungal Symbiotic Biology": {"Country": "China", "Works": {"2025": 0, "2024": 2}}, "Instituto de Investigaciones Geogr\u00e1ficas de la Patagonia": {"Country": "Argentina", "Works": {"2024": 0, "2023": 0, "2021": 0, "2020": 1, "2019": 1}}, "Escuela Normal de Zumpango": {"Country": "Mexico", "Works": {"2020": 1, "2014": 0, "2013": 1}}, "Phu Yen Vocational College": {"Country": "Vietnam", "Works": {"2023": 1, "2019": 1}}, "University of Belgrade \u2013 Faculty of Security Studies": {"Country": "Serbia", "Works": {"2024": 1, "2023": 1}}, "Escuela Normal Superior Federal de Aguascalientes \"Profr. Jos\u00e9 Santos Vald\u00e9s\"": {"Country": "Mexico", "Works": {"2024": 0, "2021": 1, "2020": 1}}, "Autonomie, G\u00e9rontologie, E-sant\u00e9, Imagerie et Soci\u00e9t\u00e9": {"Country": "France", "Works": {"2025": 0, "2024": 0, "2023": 0, "2022": 1, "2021": 0, "2020": 0, "2019": 0, "2018": 0, "2017": 1}}, "Institut Sup\u00e9rieur d\u2019Informatique et de Gestion de Goma": {"Country": "DR Congo", "Works": {"2013": 0, "2012": 0}}, "Catavento Instituto": {"Country": "Brazil", "Works": {"2024": 1, "2023": 1}}, "Leipzig Research Centre Global Dynamics": {"Country": "Germany", "Works": {"2025": 0, "2021": 2}}, "Rocket Force Sergeant School": {"Country": "China", "Works": {"2020": 1, "2019": 1}}, "Maine College of Health Professions": {"Country": "United States", "Works": {"2020": 1, "2016": 1}}, "Patel Institute of Science and Management": {"Country": "India", "Works": {"2025": 0, "2023": 1, "2022": 1}}, "Instituto Polit\u00e9cnico Jean Piaget do Sul": {"Country": "Portugal", "Works": {"2020": 1, "2019": 1}}, "Universidad Ciudadana de Nuevo Le\u00f3n": {"Country": "Mexico", "Works": {"2022": 0, "2020": 2}}, "Bader College": {"Country": "United Kingdom", "Works": {"2024": 0, "2023": 2}}, "Escola de Sa\u00fade P\u00fablica do Distrito Federal": {"Country": "Brazil", "Works": {"2025": 1, "2024": 1}}, "Kentucky Mountain Bible College": {"Country": "United States", "Works": {"2021": 0, "2018": 0, "2016": 0, "2015": 0, "2014": 0, "2013": 0}}, "Bishop State Community College": {"Country": "United States", "Works": {"2025": 0, "2024": 0, "2023": 0, "2020": 0, "2019": 0, "2018": 0, "2017": 0, "2016": 0, "2015": 0, "2014": 0, "2012": 0}}, "Glasgow Clyde College": {"Country": "United Kingdom", "Works": {"2025": 0, "2024": 0, "2023": 0, "2022": 0, "2021": 0, "2020": 0, "2019": 0, "2018": 0, "2017": 1}}, "Heisei College of Music": {"Country": "Japan", "Works": {"2023": 0, "2020": 1}}, "Williamson College of the Trades": {"Country": "United States", "Works": {"2021": 1}}, "Australian Maritime and Fisheries Academy": {"Country": "Australia", "Works": {"2022": 0, "2020": 0, "2018": 0, "2015": 0, "2014": 0, "2013": 0, "2012": 0}}, "Delta Greely School District": {"Country": "United States", "Works": {"2025": 1}}, "Institut Dr. Flad": {"Country": "Germany", "Works": {"2020": 0}}, "Chess in the Schools": {"Country": "United States", "Works": {"2023": 1}}, "Universidad Especializada del Contador P\u00fablico Autorizado": {"Country": "Panama", "Works": {"2024": 0, "2023": 0, "2022": 0, "2021": 0, "2020": 0, "2019": 1}}, "Universidad Interglobal": {"Country": "Mexico", "Works": {}}, "Koganei Daiichi Elementary School": {"Country": "Japan", "Works": {"2022": 0, "2013": 0}}, "Institut zur F\u00f6rderung von Bildung und Integration": {"Country": "Germany", "Works": {}}}